autora/experimentalist/sampler/novelty/__init__.py
autora_novelty_sampler-1.0.0a0.dist-info/METADATA
autora_novelty_sampler-1.0.0a0.dist-info/WHEEL
autora_novelty_sampler-1.0.0a0.dist-info/top_level.txt
autora_novelty_sampler-1.0.0a0.dist-info/RECORD
