Metadata-Version: 2.1
Name: autora-novelty-sampler
Version: 1.0.0a0
Summary: AutoRA Novelty Experimentalist
Author-email: Sebastian Musslick <sebastian@musslick.de>
License: MIT License
Project-URL: homepage, http://www.empiricalresearch.ai
Project-URL: repository, https://github.com/AutoResearch/autora-novelty-sampler
Project-URL: documentation, https://autoresearch.github.io/autora/
Requires-Python: <3.11,>=3.8.10
Requires-Dist: autora-core
Provides-Extra: dev
Requires-Dist: autora-core[dev] ; extra == 'dev'
